tars/__init__.py
tars/cli.py
tars/tars.py
tars/evaluators/__init__.py
tars/evaluators/abstract_evaluator.py
tars/evaluators/base_evaluator.py
tars/evaluators/trader_evaluator.py
tars/markets/__init__.py
tars/markets/abstract_market.py
tars/markets/crypto_market.py
tars/portfolios/__init__.py
tars/portfolios/abstract_portfolio.py
tars/portfolios/crypto_portfolio.py
tars/portfolios/virtual_portfolio.py
tars/strategies/__init__.py
tars/strategies/abstract_strategy.py
tars/strategies/buy_and_hold_strategy.py
tars/strategies/prediction_strategy.py
tars/strategies/random_investment_strategy.py
tars/strategies/sequential_investment_strategy.py
tars/strategies/trend_following_macd_strategy.py
tars/strategies/trend_following_strategy.py
tars/traders/__init__.py
tars/traders/abstract_trader.py
tars/traders/crypto_trader.py
tars/traders/virtual_crypto_trader.py
tars/utils/__init__.py
tars/utils/data.py
tars/utils/metrics.py
tars/utils/runner.py
tars-0.5.0.dist-info/LICENSE
tars-0.5.0.dist-info/METADATA
tars-0.5.0.dist-info/WHEEL
tars-0.5.0.dist-info/entry_points.txt
tars-0.5.0.dist-info/top_level.txt
tars-0.5.0.dist-info/RECORD
