Metadata-Version: 2.1
Name: tars
Version: 0.5.0
Summary: A crypto trading bot for research and developers
Home-page: UNKNOWN
Author: Fred Montet
License: MIT
Platform: UNKNOWN
License-File: LICENSE
Requires-Dist: pandas
Requires-Dist: click
Requires-Dist: requests
Requires-Dist: pykrakenapi
Requires-Dist: krakenex
Requires-Dist: matplotlib
Requires-Dist: prophet
Requires-Dist: torch
Requires-Dist: darts
Requires-Dist: holidays
Requires-Dist: seaborn
Requires-Dist: scipy
Requires-Dist: ta
